google/cloud/run/__init__.py
google/cloud/run/gapic_version.py
google/cloud/run/py.typed
google/cloud/run_v2/__init__.py
google/cloud/run_v2/gapic_metadata.json
google/cloud/run_v2/gapic_version.py
google/cloud/run_v2/py.typed
google/cloud/run_v2/services/__init__.py
google/cloud/run_v2/services/builds/__init__.py
google/cloud/run_v2/services/builds/async_client.py
google/cloud/run_v2/services/builds/client.py
google/cloud/run_v2/services/builds/transports/__init__.py
google/cloud/run_v2/services/builds/transports/base.py
google/cloud/run_v2/services/builds/transports/grpc.py
google/cloud/run_v2/services/builds/transports/grpc_asyncio.py
google/cloud/run_v2/services/builds/transports/rest.py
google/cloud/run_v2/services/builds/transports/rest_base.py
google/cloud/run_v2/services/executions/__init__.py
google/cloud/run_v2/services/executions/async_client.py
google/cloud/run_v2/services/executions/client.py
google/cloud/run_v2/services/executions/pagers.py
google/cloud/run_v2/services/executions/transports/__init__.py
google/cloud/run_v2/services/executions/transports/base.py
google/cloud/run_v2/services/executions/transports/grpc.py
google/cloud/run_v2/services/executions/transports/grpc_asyncio.py
google/cloud/run_v2/services/executions/transports/rest.py
google/cloud/run_v2/services/executions/transports/rest_base.py
google/cloud/run_v2/services/jobs/__init__.py
google/cloud/run_v2/services/jobs/async_client.py
google/cloud/run_v2/services/jobs/client.py
google/cloud/run_v2/services/jobs/pagers.py
google/cloud/run_v2/services/jobs/transports/__init__.py
google/cloud/run_v2/services/jobs/transports/base.py
google/cloud/run_v2/services/jobs/transports/grpc.py
google/cloud/run_v2/services/jobs/transports/grpc_asyncio.py
google/cloud/run_v2/services/jobs/transports/rest.py
google/cloud/run_v2/services/jobs/transports/rest_base.py
google/cloud/run_v2/services/revisions/__init__.py
google/cloud/run_v2/services/revisions/async_client.py
google_cloud_run-0.10.18.dist-info/LICENSE
google_cloud_run-0.10.18.dist-info/METADATA
google_cloud_run-0.10.18.dist-info/WHEEL
google_cloud_run-0.10.18.dist-info/top_level.txt
google_cloud_run-0.10.18.dist-info/RECORD
